<Properties StartupConfiguration="{7778EC7B-A304-4CDD-B3CF-218D4AD8B600}|Default">
  <MonoDevelop.Ide.ItemProperties.Tyyppimuunnokset PreferredExecutionTarget="MonoDevelop.Default" />
  <MonoDevelop.Ide.Workbench ActiveDocument="Tyyppimuunnokset/Ohjelma.cs">
    <Files>
      <File FileName="Tyyppimuunnokset/Ohjelma.cs" Line="165" Column="2" />
    </Files>
    <Pads>
      <Pad Id="ProjectPad">
        <State name="__root__">
          <Option id="ShowVersionControlOverlays" value="False" />
          <Node name="Tyyppimuunnokset" expanded="True">
            <Node name="Tyyppimuunnokset" expanded="True">
              <Node name="Ohjelma.cs" selected="True" />
            </Node>
          </Node>
        </State>
      </Pad>
    </Pads>
  </MonoDevelop.Ide.Workbench>
  <MonoDevelop.Ide.DebuggingService.PinnedWatches>
    <Watch file="../../../../../Projects/example/example/:example_2.cs" line="27" column="0" endLine="0" endColumn="0" offsetX="-1" offsetY="-1" expression="tulot" liveUpdate="False" />
    <Watch file="../../../../Teht_4_1_arva_numero/Teht_4_1_arva_numero/Teht4_1.cs" line="20" column="12" endLine="20" endColumn="19" offsetX="-1" offsetY="-1" expression="Console" liveUpdate="False" />
  </MonoDevelop.Ide.DebuggingService.PinnedWatches>
  <MonoDevelop.Ide.Workspace ActiveConfiguration="Release|anycpu" />
  <MonoDevelop.Ide.DebuggingService.Breakpoints>
    <BreakpointStore />
  </MonoDevelop.Ide.DebuggingService.Breakpoints>
  <MultiItemStartupConfigurations />
</Properties>